pythonBLEperipheral/__init__.py
pythonBLEperipheral/advertisement.py
pythonBLEperipheral/bletools.py
pythonBLEperipheral/service.py
pythonBLEperipheral-0.0.4.dist-info/LICENSE
pythonBLEperipheral-0.0.4.dist-info/LICENSE-Douglas6
pythonBLEperipheral-0.0.4.dist-info/METADATA
pythonBLEperipheral-0.0.4.dist-info/WHEEL
pythonBLEperipheral-0.0.4.dist-info/top_level.txt
pythonBLEperipheral-0.0.4.dist-info/RECORD
