Metadata-Version: 2.1
Name: pythonBLEperipheral
Version: 0.0.4
Summary: Library supporting BLE peripheral applications
Author-email: Christoph Willing <chris.willing@linux.com>, Douglas Otwell <Douglas6@github.com>
Project-URL: Homepage, https://gitlab.com/chris.willing/python-ble-peripheral
Project-URL: Bug Tracker, https://gitlab.com/chris.willing/python-ble-peripheral/issues
Classifier: Programming Language :: Python :: 3
Classifier: License :: OSI Approved :: MIT License
Classifier: Operating System :: OS Independent
Requires-Python: >=3.0
License-File: LICENSE
License-File: LICENSE-Douglas6
